indico_plugin_phonebook/__init__.py
indico_plugin_phonebook/forms.py
indico_plugin_phonebook/plugin.py
indico_plugin_phonebook-1.0.1.dist-info/METADATA
indico_plugin_phonebook-1.0.1.dist-info/WHEEL
indico_plugin_phonebook-1.0.1.dist-info/entry_points.txt
indico_plugin_phonebook-1.0.1.dist-info/top_level.txt
indico_plugin_phonebook-1.0.1.dist-info/RECORD
