Metadata-Version: 2.4
Name: indico-plugin-phonebook
Version: 1.0.1
Summary: Webhook endpoint to sync categories from the phonebook
Author: You
Author-email: Vincent Garonne <vincent.garonne@bnl.gov>
License: MIT
Project-URL: Homepage, https://git.racf.bnl.gov/gitea/CDS/indico-plugin-phonebook
Requires-Python: >=3.7
Requires-Dist: requests>=2.32.3
Requires-Dist: jsonschema>=4.23.0
Dynamic: author
